{
   "Constable Zuvio" : {
      "AbilityType" : "Abilities.SecondEdition.ConstableZuvioAbility",
      "ability" : "If you would drop a device, you may launch it using a [1 [Straight]] template instead.",
      "artwork" : "https://sb-cdn.fantasyflightgames.com/card_art/Card_art_XW_P_161.jpg",
      "caption" : "Missing Sheriff of Nima Outpost",
      "charges" : null,
      "cost" : 33,
      "faction" : "Scum and Villainy",
      "ffg" : 161,
      "force" : null,
      "image" : "https://sb-cdn.fantasyflightgames.com/card_images/Card_Pilot_161.png",
      "initiative" : 4,
      "limited" : 1,
      "name" : "Constable Zuvio",
      "ship" : "Quadrijet Transfer Spacetug",
      "ship_ffg" : 9,
      "ship_xws" : "quadrijettransferspacetug",
      "slots" : [
         "Talent",
         "Tech",
         "Crew",
         "Device",
         "Illicit",
         "Modification"
      ],
      "xws" : "constablezuvio"
   },
   "Jakku Gunrunner" : {
      "AbilityType" : "Abilities.SecondEdition.SarcoPlankAbility",
      "ability" : null,
      "artwork" : "https://sb-cdn.fantasyflightgames.com/card_art/Card_art_XW_P_164.jpg",
      "caption" : null,
      "charges" : null,
      "cost" : 28,
      "faction" : "Scum and Villainy",
      "ffg" : 164,
      "force" : null,
      "image" : "https://sb-cdn.fantasyflightgames.com/card_images/Card_Pilot_164.png",
      "initiative" : 1,
      "limited" : 0,
      "name" : "Jakku Gunrunner",
      "ship" : "Quadrijet Transfer Spacetug",
      "ship_ffg" : 9,
      "ship_xws" : "quadrijettransferspacetug",
      "slots" : [
         "Tech",
         "Crew",
         "Device",
         "Illicit",
         "Modification"
      ],
      "xws" : "jakkugunrunner"
   },
   "Sarco Plank" : {
      "ability" : "While you defend, you may treat your agility value as equal to the speed of the maneuver you executed this round.",
      "artwork" : "https://sb-cdn.fantasyflightgames.com/card_art/Card_art_XW_P_162.jpg",
      "caption" : "The Scavenger",
      "charges" : null,
      "cost" : 31,
      "faction" : "Scum and Villainy",
      "ffg" : 162,
      "force" : null,
      "image" : "https://sb-cdn.fantasyflightgames.com/card_images/Card_Pilot_162.png",
      "initiative" : 2,
      "limited" : 1,
      "name" : "Sarco Plank",
      "ship" : "Quadrijet Transfer Spacetug",
      "ship_ffg" : 9,
      "ship_xws" : "quadrijettransferspacetug",
      "slots" : [
         "Tech",
         "Crew",
         "Device",
         "Illicit",
         "Modification"
      ],
      "xws" : "sarcoplank"
   },
   "Unkar Plutt" : {
      "AbilityType" : "Abilities.SecondEdition.UnkarPluttAbility",
      "ability" : "At the start of the Engagement Phase, if there are one or more other ships at range 0, you and each other ship at range 0 gain 1 tractor token.",
      "artwork" : "https://sb-cdn.fantasyflightgames.com/card_art/Card_art_XW_P_163.jpg",
      "caption" : "Miserly Portion Master",
      "charges" : null,
      "cost" : 30,
      "faction" : "Scum and Villainy",
      "ffg" : 163,
      "force" : null,
      "image" : "https://sb-cdn.fantasyflightgames.com/card_images/Card_Pilot_163.png",
      "initiative" : 2,
      "limited" : 1,
      "name" : "Unkar Plutt",
      "ship" : "Quadrijet Transfer Spacetug",
      "ship_ffg" : 9,
      "ship_xws" : "quadrijettransferspacetug",
      "slots" : [
         "Tech",
         "Crew",
         "Device",
         "Illicit",
         "Modification"
      ],
      "xws" : "unkarplutt"
   }
}
